elecboltz/__init__.py
elecboltz/bandstructure.py
elecboltz/conductivity.py
elecboltz/fit.py
elecboltz/integrate.py
elecboltz/load.py
elecboltz/params.py
elecboltz/scattering.py
elecboltz-0.3.8.dist-info/licenses/LICENSE
elecboltz-0.3.8.dist-info/METADATA
elecboltz-0.3.8.dist-info/WHEEL
elecboltz-0.3.8.dist-info/top_level.txt
elecboltz-0.3.8.dist-info/RECORD
