Metadata-Version: 2.4
Name: elecboltz
Version: 0.3.8
Summary: Boltzmann transport for conductivity of materials using an FEM
Author-email: Saleh Shamloo Ahmadi <slhshamloo@gmail.com>
License-Expression: MIT
Project-URL: homepage, https://github.com/slhshamloo/boltzmann-conductivity
Project-URL: documentation, https://elecboltz.readthedocs.io/
Project-URL: repository, https://github.com/slhshamloo/boltzmann-conductivity
Project-URL: issues, https://github.com/slhshamloo/boltzmann-conductivity/issues
Requires-Python: >=3.9
License-File: LICENSE
Requires-Dist: numpy>=1.26.4
Requires-Dist: scipy>=1.12.0
Requires-Dist: sympy>=1.10.1
Requires-Dist: scikit-image>=0.22.0
Dynamic: license-file
